dorgy/AGENTS.md
dorgy/__init__.py
dorgy/__main__.py
dorgy/shutdown.py
dorgy/classification/AGENTS.md
dorgy/classification/__init__.py
dorgy/classification/cache.py
dorgy/classification/dspy_logging.py
dorgy/classification/engine.py
dorgy/classification/exceptions.py
dorgy/classification/models.py
dorgy/classification/structure.py
dorgy/classification/vision.py
dorgy/cli/AGENTS.md
dorgy/cli/__init__.py
dorgy/cli/app.py
dorgy/cli/context.py
dorgy/cli/lazy.py
dorgy/cli/commands/config.py
dorgy/cli/commands/mv.py
dorgy/cli/commands/org.py
dorgy/cli/commands/search.py
dorgy/cli/commands/status.py
dorgy/cli/commands/undo.py
dorgy/cli/commands/version.py
dorgy/cli/commands/watch.py
dorgy/cli/helpers/classification.py
dorgy/cli/helpers/configuration.py
dorgy/cli/helpers/formatting.py
dorgy/cli/helpers/messages.py
dorgy/cli/helpers/options.py
dorgy/cli/helpers/organization.py
dorgy/cli/helpers/parsing.py
dorgy/cli/helpers/progress.py
dorgy/cli/helpers/prompts.py
dorgy/cli/helpers/search.py
dorgy/cli/helpers/state.py
dorgy/config/AGENTS.md
dorgy/config/__init__.py
dorgy/config/exceptions.py
dorgy/config/models.py
dorgy/config/resolver.py
dorgy/ingestion/AGENTS.md
dorgy/ingestion/__init__.py
dorgy/ingestion/detectors.py
dorgy/ingestion/discovery.py
dorgy/ingestion/extractors.py
dorgy/ingestion/models.py
dorgy/ingestion/pipeline.py
dorgy/organization/AGENTS.md
dorgy/organization/__init__.py
dorgy/organization/executor.py
dorgy/organization/models.py
dorgy/organization/planner.py
dorgy/search/AGENTS.md
dorgy/search/__init__.py
dorgy/search/index.py
dorgy/search/lifecycle.py
dorgy/search/text.py
dorgy/state/AGENTS.md
dorgy/state/__init__.py
dorgy/state/errors.py
dorgy/state/models.py
dorgy/watch/AGENTS.md
dorgy/watch/__init__.py
dorgy/watch/service.py
dorgy-0.5.4.dist-info/METADATA
dorgy-0.5.4.dist-info/WHEEL
dorgy-0.5.4.dist-info/entry_points.txt
dorgy-0.5.4.dist-info/licenses/LICENSE
dorgy-0.5.4.dist-info/RECORD
