Metadata-Version: 2.4
Name: dorgy
Version: 0.5.4
Summary: AI-assisted CLI for organizing files.
Project-URL: Homepage, https://github.com/bryaneburr/dorgy
Project-URL: Bug Tracker, https://github.com/bryaneburr/dorgy/issues
Project-URL: Documentation, https://bryaneburr.github.io/dorgy/
Author: Bryan E. Burr
License: MIT License
License-File: LICENSE
Keywords: ai,automation,cli,document organization,productivity
Classifier: Development Status :: 3 - Alpha
Classifier: Intended Audience :: Developers
Classifier: Intended Audience :: System Administrators
Classifier: License :: OSI Approved :: MIT License
Classifier: Operating System :: OS Independent
Classifier: Programming Language :: Python
Classifier: Programming Language :: Python :: 3
Classifier: Programming Language :: Python :: 3.11
Classifier: Programming Language :: Python :: 3.12
Classifier: Programming Language :: Python :: 3.13
Classifier: Topic :: Office/Business
Classifier: Topic :: Software Development :: Build Tools
Classifier: Topic :: Utilities
Requires-Python: >=3.11
Requires-Dist: chromadb>=0.5.0
Requires-Dist: click>=8.0.0
Requires-Dist: docling>=1.0.0
Requires-Dist: dspy>=2.0.0
Requires-Dist: durango>=0.1.3
Requires-Dist: pillow-avif-plugin>=1.5.2
Requires-Dist: pillow-heif>=1.1.1
Requires-Dist: pillow-jxl-plugin>=1.3.5
Requires-Dist: pillow>=10.0.0
Requires-Dist: pydantic>=2.5
Requires-Dist: python-magic>=0.4.27
Requires-Dist: pyyaml>=6.0
Requires-Dist: rich>=13.0.0
Requires-Dist: tqdm>=4.0.0
Requires-Dist: watchdog>=3.0.0
Requires-Dist: xxhash>=3.4.1
Provides-Extra: dev
Requires-Dist: invoke>=2.2.0; extra == 'dev'
Requires-Dist: mypy>=1.9.0; extra == 'dev'
Requires-Dist: pre-commit>=3.7.0; extra == 'dev'
Requires-Dist: pytest>=8.0.0; extra == 'dev'
Requires-Dist: ruff>=0.6.0; extra == 'dev'
Requires-Dist: types-pyyaml>=6.0.12.20240917; extra == 'dev'
Provides-Extra: docs
Requires-Dist: mkdocs-click>=0.8.1; extra == 'docs'
Requires-Dist: mkdocs-shadcn>=0.1.6; extra == 'docs'
Requires-Dist: mkdocs>=1.5.3; extra == 'docs'
Requires-Dist: mkdocstrings[python]>=0.24.0; extra == 'docs'
Requires-Dist: pymdown-extensions>=10.0; extra == 'docs'
